<?xml version="1.0" encoding="utf-8" ?><dwsync><file name="blog.php" local="-3698908784018587648" remote="-3698908784018587648" testing="-3698908784018587648" /><file name="index.php" local="-3698908784018587648" remote="-3698908784018587648" testing="-3698908784018587648" /><file name="insert.php" local="-3698908784018587648" remote="-3698908784018587648" testing="-3698908784018587648" /><file name="redovisning.php" local="-3698908784018587648" remote="-3698908784018587648" testing="-3698908784018587648" /><file name="login.php" local="-3698166806943367168" remote="-3698166806943367168" testing="-3698166806943367168" /><file name="logout.php" local="-3698166678094348288" remote="-3698166678094348288" testing="-3698166678094348288" /><file name="newuser.php" local="-3698165930770038784" remote="-3698165930770038784" testing="-3698165930770038784" /><file name="edituser.php" local="-3698167438303559680" remote="-3698167438303559680" testing="-3698167438303559680" /><file name="dbupdated.php" local="-3698168915772309504" remote="-3698168915772309504" testing="-3698168915772309504" /></dwsync>